f2/__init__.py
f2/__main__.py
f2/helps.py
f2/apps/__apps__.py
f2/apps/__init__.py
f2/apps/douyin/api.py
f2/apps/douyin/cli.py
f2/apps/douyin/crawler.py
f2/apps/douyin/db.py
f2/apps/douyin/dl.py
f2/apps/douyin/filter.py
f2/apps/douyin/handler.py
f2/apps/douyin/help.py
f2/apps/douyin/model.py
f2/apps/douyin/utils.py
f2/apps/douyin/algorithm/webcast_signature.js
f2/apps/douyin/algorithm/webcast_signature.py
f2/apps/douyin/proto/douyin_webcast.proto
f2/apps/douyin/proto/douyin_webcast_pb2.py
f2/apps/douyin/test/test_douyin_apps_model.py
f2/apps/douyin/test/test_douyin_aweme_id.py
f2/apps/douyin/test/test_douyin_crawler.py
f2/apps/douyin/test/test_douyin_handler.py
f2/apps/douyin/test/test_douyin_lrc.py
f2/apps/douyin/test/test_douyin_room_id.py
f2/apps/douyin/test/test_douyin_sec_user_id.py
f2/apps/douyin/test/test_douyin_token.py
f2/apps/douyin/test/test_douyin_webcast_id.py
f2/apps/douyin/test/test_douyin_webcast_signature.py
f2/apps/tiktok/api.py
f2/apps/tiktok/cli.py
f2/apps/tiktok/crawler.py
f2/apps/tiktok/db.py
f2/apps/tiktok/dl.py
f2/apps/tiktok/filter.py
f2/apps/tiktok/handler.py
f2/apps/tiktok/help.py
f2/apps/tiktok/model.py
f2/apps/tiktok/utils.py
f2/apps/tiktok/test/test_tiktok_crawler.py
f2/apps/tiktok/test/test_tiktok_device_id.py
f2/apps/tiktok/test/test_tiktok_token.py
f2/apps/twitter/api.py
f2/apps/twitter/cli.py
f2/apps/twitter/crawler.py
f2/apps/twitter/db.py
f2/apps/twitter/dl.py
f2/apps/twitter/filter.py
f2/apps/twitter/handler.py
f2/apps/twitter/help.py
f2/apps/twitter/model.py
f2/apps/twitter/utils.py
f2/apps/twitter/test/test_model.py
f2/apps/twitter/test/test_tweet_id.py
f2/apps/weibo/api.py
f2/apps/weibo/cli.py
f2/apps/weibo/crawler.py
f2/apps/weibo/db.py
f2/apps/weibo/dl.py
f2/apps/weibo/filter.py
f2/apps/weibo/handler.py
f2/apps/weibo/help.py
f2/apps/weibo/model.py
f2/apps/weibo/utils.py
f2/apps/weibo/test/test_gen_visitor.py
f2/apps/weibo/test/test_handler.py
f2/apps/weibo/test/test_weibo_id.py
f2/apps/weibo/test/test_weibo_uid.py
f2-0.0.1.6.dist-info/METADATA
f2-0.0.1.6.dist-info/WHEEL
f2-0.0.1.6.dist-info/entry_points.txt
f2-0.0.1.6.dist-info/licenses/LICENSE
f2-0.0.1.6.dist-info/RECORD
