Metadata-Version: 2.3
Name: f2
Version: 0.0.1.6
Summary: 🚀Asynchronous based full-platform download tool
Project-URL: Homepage, https://github.com/Johnserf-Seed/f2
Project-URL: Documentation, https://johnserf-seed.github.io/f2/
Project-URL: Chat, https://discord.gg//3PhtPmgHf8
Project-URL: Source Code, https://github.com/Johnserf-Seed/f2
Project-URL: Issue Tracker, https://github.com/Johnserf-Seed/f2/issues
Author-email: Johnserf-Seed <johnserf-seed@foxmail.com>
License-Expression: Apache-2.0
License-File: LICENSE
Classifier: Intended Audience :: Customer Service
Classifier: Intended Audience :: Developers
Classifier: License :: OSI Approved :: Apache Software License
Classifier: Programming Language :: Python :: 3
Classifier: Programming Language :: Python :: 3 :: Only
Classifier: Programming Language :: Python :: 3.9
Classifier: Programming Language :: Python :: 3.10
Classifier: Programming Language :: Python :: 3.11
Requires-Python: >=3.9
Requires-Dist: aiofiles==22.1.0
Requires-Dist: aiosqlite==0.20.0
Requires-Dist: browser-cookie3==0.19.1
Requires-Dist: click==8.1.7
Requires-Dist: gmssl==3.2.2
Requires-Dist: httpx==0.27.0
Requires-Dist: importlib-resources==6.1.0
Requires-Dist: jsonpath-ng==1.6.0
Requires-Dist: m3u8==3.6.0
Requires-Dist: protobuf==4.23.0
Requires-Dist: pydantic==2.6.4
Requires-Dist: pyexecjs==1.5.1
Requires-Dist: pytest-asyncio==0.21.1
Requires-Dist: pytest==8.2.1
Requires-Dist: pyyaml==6.0.1
Requires-Dist: qrcode==7.4.2
Requires-Dist: rich==13.7.1
Requires-Dist: websockets>=11.0
